{"cameraMode":{"drawMode":0,"name":"Shaded","section":"Shading Mode"},"sceneLighting":true,"audioPlay":false,"sceneViewState":{"m_AlwaysRefresh":false,"showFog":true,"showSkybox":true,"showFlares":true,"showImageEffects":true,"showParticleSystems":true,"showVisualEffectGraphs":true,"m_FxEnabled":true},"in2DMode":false,"pivot":{"x":437.47259521484377,"y":36.07566833496094,"z":-316.9617919921875},"rotation":{"x":-0.0028554536402225496,"y":0.9949304461479187,"z":-0.09611855447292328,"w":-0.02955695241689682},"size":603.0215454101563,"orthographic":false}